nicholima_csv_converter/__init__.py
nicholima_csv_converter/converter.py
nicholima_csv_converter/converterjs.py
nicholima_csv_converter-0.1.1.dist-info/entry_points.txt
nicholima_csv_converter-0.1.1.dist-info/WHEEL
nicholima_csv_converter-0.1.1.dist-info/METADATA
nicholima_csv_converter-0.1.1.dist-info/RECORD
