Metadata-Version: 2.1
Name: nicholima-csv-converter
Version: 0.1.1
Summary: Converter csv to json.
Author: Nicholas Lima
Author-email: nicho.lima@gmail.com
Requires-Python: >=3.8,<4.0
Classifier: Programming Language :: Python :: 3
Classifier: Programming Language :: Python :: 3.10
Classifier: Programming Language :: Python :: 3.8
Classifier: Programming Language :: Python :: 3.9
Requires-Dist: click (>=8.0.3,<9.0.0)
